{
  "description": "项目私有配置文件。此文件中的内容将覆盖 project.config.json 中的相同字段。项目的改动优先同步到此文件中。详见文档：https://developers.weixin.qq.com/miniprogram/dev/devtools/projectconfig.html",
  "condition": {
    "miniprogram": {
      "list": [
        {
          "name": "",
          "pathName": "pages/goodsSearch/index",
          "query": "",
          "launchMode": "default",
          "scene": null
        },
        {
          "name": "",
          "pathName": "pages/goodsDetails/index",
          "query": "id=37",
          "launchMode": "default",
          "scene": null
        },
        {
          "name": "",
          "pathName": "pages/order/index",
          "query": "",
          "launchMode": "default",
          "scene": null
        },
        {
          "name": "",
          "pathName": "pages/address/index",
          "query": "",
          "launchMode": "default",
          "scene": null
        },
        {
          "name": "",
          "pathName": "pages/addressManage/index",
          "query": "id=undefined",
          "launchMode": "default",
          "scene": null
        },
        {
          "name": "",
          "pathName": "pages/myIndex/index",
          "query": "",
          "launchMode": "default",
          "scene": null
        },
        {
          "name": "",
          "pathName": "pages/orderList/index",
          "query": "order=0",
          "launchMode": "default",
          "scene": null
        },
        {
          "name": "",
          "pathName": "pages/orderDetails/index",
          "query": "id=230405193420720155",
          "launchMode": "default",
          "scene": null
        },
        {
          "name": "",
          "pathName": "pages/index/index",
          "query": "ch=123",
          "launchMode": "default",
          "scene": null
        },
        {
          "name": "",
          "pathName": "pages/orderDetails/index",
          "query": "id=230408153307318221",
          "launchMode": "default",
          "scene": null
        },
        {
          "name": "",
          "pathName": "pages/returnGoods/index",
          "query": "id=230409102928674984",
          "launchMode": "default",
          "scene": null
        },
        {
          "name": "",
          "pathName": "pages/returnGoods/index",
          "query": "id=3",
          "launchMode": "default",
          "scene": null
        },
        {
          "name": "",
          "pathName": "pages/returnDetails/index",
          "query": "id=3",
          "launchMode": "default",
          "scene": null
        },
        {
          "name": "",
          "pathName": "pages/logistics/index",
          "query": "log_info=%7B%22logistics_no%22%3A%22YT7158751078163%22%2C%22picture_list%22%3A%5B%22https%3A%2F%2Fstatic.zjkdongao.com%2FshowImage%2FBpRBrB9szCsEe42f98e8921442ab3792a5b84980fcfc.jpeg%22%2C%22https%3A%2F%2Fstatic.zjkdongao.com%2FshowImage%2FN3JEdrgsackEded5d2c71ce201e0aeda9edd2e5fc6e8.jpeg%22%5D%2C%22logistics_company%22%3A%22YTO%22%2C%22address_detail%22%3A%22%E5%8C%97%E4%BA%AC%E5%B8%82%E5%8C%97%E4%BA%AC%E5%B8%82%E4%B8%B0%E5%8F%B0%E5%8C%BA%E7%83%9F%E5%8E%82%E5%AE%BF%E8%88%8D37-2-503%22%7D",
          "launchMode": "default",
          "scene": null
        },
        {
          "name": "",
          "pathName": "pages/logistics/index",
          "query": "log_info=%7B%22logistics_no%22%3A%22YT7158751078163%22%2C%22picture_list%22%3A%5B%22https%3A%2F%2Fstatic.zjkdongao.com%2FshowImage%2FBpRBrB9szCsEe42f98e8921442ab3792a5b84980fcfc.jpeg%22%2C%22https%3A%2F%2Fstatic.zjkdongao.com%2FshowImage%2FN3JEdrgsackEded5d2c71ce201e0aeda9edd2e5fc6e8.jpeg%22%5D%2C%22logistics_company%22%3A%22YTO%22%2C%22address_detail%22%3A%22%E5%8C%97%E4%BA%AC%E5%B8%82%E5%8C%97%E4%BA%AC%E5%B8%82%E4%B8%B0%E5%8F%B0%E5%8C%BA%E7%83%9F%E5%8E%82%E5%AE%BF%E8%88%8D37-2-503%22%7D",
          "launchMode": "default",
          "scene": null
        },
        {
          "name": "",
          "pathName": "pages/classification/index",
          "query": "",
          "launchMode": "default",
          "scene": null
        },
        {
          "name": "",
          "pathName": "pages/orderDetails/index",
          "query": "id=FMM230426155758576316",
          "launchMode": "default",
          "scene": null
        },
        {
          "name": "",
          "pathName": "pages/classification/index",
          "query": "",
          "launchMode": "default",
          "scene": null
        },
        {
          "name": "",
          "pathName": "pages/protocol/index",
          "query": "",
          "launchMode": "default",
          "scene": null
        }
      ]
    }
  },
  "setting": {
    "compileHotReLoad": true,
    "urlCheck": false,
    "bigPackageSizeSupport": false
  },
  "libVersion": "3.4.9",
  "projectname": "%E8%82%A5%E7%8C%AB%E7%8C%AB%E6%83%85%E8%B6%A3%E5%95%86%E5%9F%8E"
}